README.rst
setup.cfg
setup.py
pubplot/__init__.py
pubplot/axes.py
pubplot/document.py
pubplot/document_classes.py
pubplot/figure.py
pubplot/helpers.py
pubplot/latex.py
pubplot/styles.py
pubplot.egg-info/PKG-INFO
pubplot.egg-info/SOURCES.txt
pubplot.egg-info/dependency_links.txt
pubplot.egg-info/requires.txt
pubplot.egg-info/top_level.txt