Metadata-Version: 1.1
Name: pubplot
Version: 0.2.4
Summary: Seamless LaTeX and Matplotlib integration for publication plots
Home-page: UNKNOWN
Author: Hugo Sadok
Author-email: hugo@sadok.com.br
License: ISC
Download-URL: https://github.com/hsadok/pubplot
Keywords: matplotlib,latex,pgf
Platform: UNKNOWN
Classifier: Development Status :: 4 - Beta
Classifier: Intended Audience :: Science/Research
Classifier: License :: OSI Approved :: ISC License (ISCL)
Classifier: Natural Language :: English
Classifier: Programming Language :: Python
Classifier: Programming Language :: Python :: 3
Classifier: Programming Language :: Python :: 3.4
Classifier: Programming Language :: Python :: 3.5
Classifier: Programming Language :: Python :: 3.6
Classifier: Programming Language :: Python :: 3.7
Classifier: Topic :: Scientific/Engineering :: Visualization
